a_pandas_ex_css_selector_from_html/LICENSE
a_pandas_ex_css_selector_from_html/README.MD
a_pandas_ex_css_selector_from_html/__init__.py
a_pandas_ex_css_selector_from_html/requirements.txt
a_pandas_ex_css_selector_from_html/thirdparty.json
a_pandas_ex_css_selector_from_html-0.10.dist-info/LICENSE.rst
a_pandas_ex_css_selector_from_html-0.10.dist-info/METADATA
a_pandas_ex_css_selector_from_html-0.10.dist-info/WHEEL
a_pandas_ex_css_selector_from_html-0.10.dist-info/top_level.txt
a_pandas_ex_css_selector_from_html-0.10.dist-info/RECORD
