Metadata-Version: 2.1
Name: a-pandas-ex-css-selector-from-html
Version: 0.10
Summary: Generates all possible CSS selector combinations from an HTML string - Speed up your Selenium automation!
Home-page: https://github.com/hansalemaos/a_pandas_ex_css_selector_from_html
Author: Johannes Fischer
Author-email: <aulasparticularesdealemaosp@gmail.com>
License: MIT
Keywords: selenium,pandas,css,html,css selector,bs4,automation
Classifier: Development Status :: 4 - Beta
Classifier: Programming Language :: Python :: 3 :: Only
Classifier: Programming Language :: Python :: 3.9
Classifier: Topic :: Scientific/Engineering :: Visualization
Classifier: Topic :: Software Development :: Libraries :: Python Modules
Classifier: Topic :: Text Editors :: Text Processing
Classifier: Topic :: Text Processing :: General
Classifier: Topic :: Text Processing :: Indexing
Classifier: Topic :: Text Processing :: Filters
Classifier: Topic :: Utilities
License-File: LICENSE.rst
Requires-Dist: a-pandas-ex-enumerate-groups
Requires-Dist: beautifulsoup4
Requires-Dist: flatten-everything
Requires-Dist: more-itertools
Requires-Dist: pandas
Requires-Dist: requests
